Workbook

Sheet Income Tracker
A1: Month | B1: Dept | C1: Pre.Rem | D1: Salary | E1: Freelance | F1: Returns | G1: Ext. Income | H1: Total Income | I1: Reg. Savings | J1: Ext. Savings | K1: Reg. Expence | L1: Ext. Expence | M1: Total Expence | N1: Dept. Payment | O1: Borrow | P1: Overhead | Q1: Ovh. Savings | R1: Total Savings | S1: Remaining | T1: Dept | U1: 0 | V1: =37743 +15973 +8436 -> 62152
A2: Aug | B2: =V1 -> 62152 | C2: 14000 | D2: 0 | E2: 0 | F2: 3000 | G2: 0 | H2: =SUM(C2:G2) -> 17000 | I2: 0 | J2: 0 | K2: 20000 | L2: =25000+27000+6000+14000 -> 72000 | M2: =SUM(K2:L2) -> 92000 | N2: 14000 | P2: =IF(H2-SUM(I2:J2)-M2>0,H2-SUM(I2:J2)-M2,0) -> 0 | Q2: =IF(P2>0,P2/2,0) -> 0 | R2: =SUM(I2:J2)+Q2 -> 0 | S2: =P2-Q2 -> 0 | T2: =(B2-N2)+O2+IF(M2>H2,M2-H2,0) -> 123152
A3: Sep | B3: =T2 -> 123152 | C3: =S2 -> 0 | D3: 0 | E3: 0 | F3: =3000+1000+2000+1000 -> 7000 | G3: =6000+2000+500+1500+1000+19000 -> 30000 | H3: =SUM(D3:G3) -> 37000 | I3: 3000 | J3: 0 | K3: =5000+4000 -> 9000 | L3: =SUMIFS('Expense Log'!D:D, 'Expense Log'!B:B, "ext", 'Expense Log'!A:A, ">=2026-09-01", 'Expense Log'!A:A, "<=2026-09-30") -> 21065 | M3: =SUM(K3:L3) -> 30065 | N3: =15000+5000+4000 -> 24000 | O3: =15000+2000+5000 -> 22000 | P3: =IF(M3+N3<H3+O3,(H3+O3)-(M3+N3),0) -> 4935 | R3: =SUM(I3:J3)+Q3 -> 3000 | S3: =P3-Q3 -> 4935 | T3: =(B3-N3)+O3+IF(M3>H3,M3-H3,0) -> 121152
A4: Oct | B4: =T3 -> 121152 | C4: =S3 -> 4935 | D4: =SUMIFS(Income!D:D,Income!B:B,"sal",Income!A:A,">=2026-10-01",Income!A:A,"<=2026-10-30") -> 0 | E4: =SUMIFS(Income!D:D,Income!B:B,"fl",Income!A:A,">=2026-10-01",Income!A:A,"<=2026-10-30") -> 7000 | F4: =SUMIFS(Returns!D:D,Returns!B:B,"rt",Returns!A:A,">=2026-10-01",Returns!A:A,"<=2026-10-30") -> 23000 | G4: =SUMIFS(Income!D:D,Income!B:B,"ext",Income!A:A,">=2026-10-01",Income!A:A,"<=2026-10-30") -> 14000 | H4: =SUM(C4:G4) -> 48935 | I4: 0 | J4: 0 | K4: =1200+1300 -> 2500 | L4: =SUMIFS('Expense Log'!D:D, 'Expense Log'!B:B, "ext", 'Expense Log'!A:A, ">=2026-10-01", 'Expense Log'!A:A, "<=2026-10-30") -> 11541 | M4: =SUM(K4:L4) -> 14041 | N4: =7718+11828+32512 -> 52058 | O4: =SUMIFS(Borrow!D:D,Borrow!B:B,"br",Borrow!A:A,">=2026-10-01",Borrow!A:A,"<=2026-10-30") -> 15541 | P4: =IF(M4+N4<H4+O4,(H4+O4)-(M4+N4),0) -> 0 | Q4: =IF(P4>0,P4/2,0) -> 0 | R4: =SUM(I4:J4)+Q4 -> 0 | S4: =P4-Q4 -> 0 | T4: =(B4-N4)+O4+IF(M4>H4,M4-H4,0) -> 84635
A5: Nov
A6: Dec
A7: Jan

Sheet Returns
A1: date | B1: category | C1: person | D1: amount
A2: 46296 | B2: rt | C2: soso | D2: 10000
A3: 46297 | B3: rt | C3: iban mian | D3: 3000
A4: 46298 | B4: rt | C4: iban main | D4: 10000

Sheet Income
A1: date | B1: category | C1: from | D1: amount
A2: 46297 | B2: fl | C2: meker | D2: 7000 | G2: fl=free lancing
A3: 46298 | B3: ext | C3: Dad | D3: 5000 | G3: ext=extra
A4: 46299 | B4: ext | C4: Dad | D4: 5000 | G4: saving = withdraw savings
A5: 46300 | B5: ext | C5: Dad | D5: 1000
A6: 46301 | B6: ext | C6: Savings | D6: 3000

Sheet Expense Log
A1: Date | B1: Category | C1: Description | D1: Amount
A2: 46266 | B2: ext | C2: utensil | D2: 2004
A3: 46267 | B3: ext | C3: gadget | D3: 2003
A4: 46268 | B4: ext | C4: holder | D4: 554
A5: 46274 | B5: ext | C5: food for home | D5: 200
A6: 46274 | B6: reg | C6: Petrol | D6: 200
A7: 46274 | B7: ext | C7: Drinks | D7: 165
A8: 46274 | B8: ext | C8: Sent money Nong | D8: 100
A9: 46274 | B9: ext | C9: fom guw to how | D9: 1400
A10: 46274 | B10: ext | C10: from how to Sili | D10: 1515
A11: 46284 | B11: ext | C11: hotel in sikkim | D11: 2600
A12: 46285 | B12: ext | C12: food in sikkim | D12: 3424
A13: 46285 | B13: ext | C13: travel sikkim | D13: =1400+1400 -> 2800
A14: 46286 | B14: ext | C14: travel to megh | D14: 1000
A15: 46287 | B15: ext | C15: food in megh | D15: 1000
A16: 46287 | B16: ext | C16: travel back | D16: 1700
A17: 46288 | B17: ext | C17: extra speds | D17: 600
A18: 46296 | B18: ext | C18: hote huwahati | D18: 2000
A19: 46297 | B19: ext | C19: birthda iban | D19: 3299
A20: 46298 | B20: ext | C20: bithday | D20: 1484
A21: 46299 | B21: ext | C21: electronics | D21: 2662
A22: 46306 | B22: ext | C22: ibans extra exp | D22: 2096

Sheet Borrow
A1: date | B1: category | C1: reason | D1: amount
A2: 46297 | B2: br | C2: iban help | D2: 4000
A3: 46298 | B3: br | C3: iban gift | D3: 3299
A4: 46299 | B4: br | C4: iban cosmetics | D4: 1484
A5: 46299 | B5: br | C5: electronics blinkit | D5: 2662
A6: 46300 | B6: br | C6: hotel guwahati | D6: 2000
A7: 46306 | B7: br | C7: for ibans funds | D7: 2096

Sheet Goals Tracker
A1: Goal | B1: Target Amount | C1: savings % | D1: Saved So Far | E1: Remaining
A2: Dad GPU | B2: 85000 | C2: 0.14
A3: Dad Camera | B3: 64000 | C3: 0.15
A4: Dad Drone | B4: 130000 | C4: 0.1
A5: Gold for Mom | B5: 200000 | C5: 0.05
A6: iPad Pro | B6: 110000 | C6: 0.3
A7: Touring Bike | B7: 600000 | C7: 0.17
A8: Land Purchase | B8: 4500000 | C8: 0.03
A9: Own Car | B9: 2400000 | C9: 0.02
A10: New House | B10: 10000000 | C10: 0.01
A11: Farmland | B11: 10000000 | C11: 0.03
A12: Farmland in Meghalaya | B12: 10000000
A48: Total | B48: =SUM(B2:B47) -> 38089000 | C48: =SUM(C2:C47) -> 1 | D48: =SUM(D2:D47) -> 0 | E48: =SUM(E2:E47) -> 0

Sheet March Summary
A1: Category | B1: Budget % | C1: Planned Amount | D1: Actual Spent
A2: Essentials | B2: 0.5
A3: Emergency Fund | B3: 0.1
A4: Parents Fund | B4: 0.13
A5: Business Growth | B5: 0.15
A6: Big Assets Fund | B6: 0.07
A7: Small Assets | B7: 0.05 | D7: 400
A8: Total | B8: =SUM(B2:B7) -> 1 | D8: =SUM(D2:D7) -> 400

Sheet travel sikkim
A1: Item | B1: Cost | D1: item | E1: cost | G1: item | H1: cost
A2: Hotel | B2: 2066 | D2: recharge | E2: 399 | G2: sumo to GUY | H2: 500
A3: Train | B3: 400 | D3: recharge | E3: 49 | G3: I. Food | H3: 100
A4: Blinkit | B4: 500 | D4: blinkit | E4: 500 | G4: Medical | H4: 75
A5: sitting | B5: 150 | D5: hotel | E5: 600 | G5: Juice | H5: 80
A6: travel | B6: 1400 | D6: food travel | E6: 40 | G6: toilet | H6: 10
A7: tibel food | B7: 1454 | D7: my food | E7: 100 | G7: laughing | H7: 60
A8: ice cream | B8: 30 | G8: Siki Toilet | H8: 10
A9: cheese cake | B9: 180 | G9: drinks | H9: =50 -> 50
A10: bimbimbap | B10: 440 | G10: momo | H10: 100
A11: food in trav | B11: 30 | G11: car to hotel | H11: 300
A12: total | B12: =SUM(B2:B11) -> 6650 | E12: =SUM(E2:E11) -> 1688 | H12: =SUM(H2:H11) -> 1285
A14: slice pay | B14: =B12+E12 -> 8338
A16: togather | B16: =B12+E12+H12 -> 9623 | C16: =B6+B7+B10+E2+E4 -> 4193 | D16: =B16-C16 -> 5430
A17: food | B17: =B10+B11+B8+B9+B7+B4+B5+E4+E6+E7 -> 3424 | J17: 7000
J18: 8944 | K18: 11718
J19: 10000 | K19: 32512
J20: 7000 | K20: 7700
J21: 6000
J22: 5000
J23: 1000
J24: 0
J25: 5000
J26: =SUM(J17:J25) -> 49944
